README.md
setup.py
error_simplesqlite.egg-info/PKG-INFO
error_simplesqlite.egg-info/SOURCES.txt
error_simplesqlite.egg-info/dependency_links.txt
error_simplesqlite.egg-info/top_level.txt
simplesqlite/__init__.py